odoo10_addon_account_invoice_merge_payment-10.0.1.0.0.99.dev3-py2.7-nspkg.pth
odoo/addons/account_invoice_merge_payment/README.rst
odoo/addons/account_invoice_merge_payment/__init__.py
odoo/addons/account_invoice_merge_payment/__manifest__.py
odoo/addons/account_invoice_merge_payment/i18n/account_invoice_merge_payment.pot
odoo/addons/account_invoice_merge_payment/i18n/fr.po
odoo/addons/account_invoice_merge_payment/i18n/sl.po
odoo/addons/account_invoice_merge_payment/models/__init__.py
odoo/addons/account_invoice_merge_payment/models/account_invoice.py
odoo/addons/account_invoice_merge_payment/static/description/icon.png
odoo10_addon_account_invoice_merge_payment-10.0.1.0.0.99.dev3.dist-info/METADATA
odoo10_addon_account_invoice_merge_payment-10.0.1.0.0.99.dev3.dist-info/RECORD
odoo10_addon_account_invoice_merge_payment-10.0.1.0.0.99.dev3.dist-info/WHEEL
odoo10_addon_account_invoice_merge_payment-10.0.1.0.0.99.dev3.dist-info/namespace_packages.txt
odoo10_addon_account_invoice_merge_payment-10.0.1.0.0.99.dev3.dist-info/top_level.txt
